lexx/__about__.py
lexx/__init__.py
lexx/__main__.py
lexx/definition.py
lexx/distribution.py
lexx/errors.py
lexx/filter.py
lexx/language.py
lexx/phonemes.py
lexx/wordgen.py
lexx/cli/__init__.py
lexx/plugins/assimilations.py
lexx/plugins/metathesis.py
lexx-0.3.0.dist-info/METADATA
lexx-0.3.0.dist-info/WHEEL
lexx-0.3.0.dist-info/entry_points.txt
lexx-0.3.0.dist-info/licenses/LICENSE
lexx-0.3.0.dist-info/RECORD
